taylor/__init__.py
taylor/error.py
taylor/main.py
taylor/rules.py
taylor-0.0.0.data/scripts/taylor
taylor-0.0.0.dist-info/LICENSE
taylor-0.0.0.dist-info/METADATA
taylor-0.0.0.dist-info/WHEEL
taylor-0.0.0.dist-info/top_level.txt
taylor-0.0.0.dist-info/RECORD
