Metadata-Version: 2.1
Name: taylor
Version: 0.0.0
Summary: Generic derivative objects (gradients, Jacobians, Hessians, and more) by finite differences
Home-page: https://github.com/ghbrown/taylor
Author: Gabriel H. Brown
Author-email: gabriel.h.brown@gmail.com
License: UNKNOWN
Keywords: scientific,engineering,derivatives,optimization,rootfinding,approximation
Platform: UNKNOWN
Classifier: Programming Language :: Python :: 3
Classifier: License :: OSI Approved :: MIT License
Classifier: Operating System :: OS Independent
Classifier: Topic :: Scientific/Engineering
License-File: LICENSE
Requires-Dist: numpy
